fastvs-0.1.8.dist-info/METADATA
fastvs-0.1.8.dist-info/WHEEL
fastvs/__init__.py
fastvs/fastvs.pyi
fastvs/fastvs.cpython-39-powerpc64le-linux-gnu.so
fastvs-0.1.8.dist-info/RECORD
