Metadata-Version: 2.1
Name: fastvs
Version: 0.1.8
